datec/__init__.py
datec/__main__.py
datec-0.1.dist-info/LICENSE
datec-0.1.dist-info/METADATA
datec-0.1.dist-info/WHEEL
datec-0.1.dist-info/entry_points.txt
datec-0.1.dist-info/top_level.txt
datec-0.1.dist-info/RECORD
