Metadata-Version: 2.1
Name: datec
Version: 0.1
Summary: Date Command
Home-page: https://github.com/isaacto/datec
Author: Isaac To
Author-email: isaac.to@gmail.com
License: UNKNOWN
Platform: UNKNOWN
Classifier: Development Status :: 4 - Beta
Classifier: Programming Language :: Python :: 2.7
Classifier: Programming Language :: Python :: 3
Classifier: Topic :: Software Development :: Libraries
Classifier: License :: OSI Approved :: MIT License
Classifier: Operating System :: OS Independent
Requires-Dist: python-dateutil
